[
  {
    "timestamp": "2025-10-03_01-52",
    "source": "JD Supra",
    "title": "Exorcising AI Myths: What's Really Haunting Your Business - Part 1",
    "url": "https://www.jdsupra.com/legalnews/exorcising-ai-myths-what-s-really-1232152/",
    "summary": "Exorcising AI Myths: What's really Haunting Your Business - Part",
    "tags": [
      "other"
    ]
  },
  {
    "timestamp": "2025-10-03_01-52",
    "source": "Nature",
    "title": "Large language models forecast patient health trajectories enabling digital twins",
    "url": "https://www.nature.com/articles/s41746-025-02004-3",
    "summary": "Large language models forecast patient health trajectories enabling digital",
    "tags": [
      "other"
    ]
  },
  {
    "timestamp": "2025-10-03_01-52",
    "source": "Precedence Research",
    "title": "Cloud-Based Machine Learning (ML) Platforms Market Size, Report by 2034",
    "url": "https://www.precedenceresearch.com/cloud-based-machine-learning-platforms-market",
    "summary": "Cloud-Based Machine Learning (ML) Platforms Market Size, Report by 20",
    "tags": [
      "other"
    ]
  },
  {
    "timestamp": "2025-10-03_01-52",
    "source": "eWeek",
    "title": "Generative AI vs Predictive AI: Exploring Creativity and Analysis",
    "url": "https://www.eweek.com/artificial-intelligence/generative-ai-vs-predictive-ai/",
    "summary": "Generative AI vs Predictive AI: Exploring Creativity and",
    "tags": [
      "other"
    ]
  },
  {
    "timestamp": "2025-10-03_01-52",
    "source": "Amazon Web Services",
    "title": "Intelligent document processing at scale with generative AI and Amazon Bedrock Data Automation | Artificial Intelligence",
    "url": "https://aws.amazon.com/blogs/machine-learning/intelligent-document-processing-at-scale-with-generative-ai-and-amazon-bedrock-data-automation/",
    "summary": "Amazon Bedrock Data Automation | Artificial Intelligence . Amazon Bedrorocks is the company behind",
    "tags": [
      "other"
    ]
  }
]